paikalta/__init__.py
paikalta/__main__.py
paikalta/api.py
paikalta/cli.py
paikalta-2025.6.9.dist-info/licenses/LICENSE
paikalta-2025.6.9.dist-info/METADATA
paikalta-2025.6.9.dist-info/WHEEL
paikalta-2025.6.9.dist-info/entry_points.txt
paikalta-2025.6.9.dist-info/top_level.txt
paikalta-2025.6.9.dist-info/RECORD
