Metadata-Version: 2.4
Name: paikalta
Version: 2025.6.9
Summary: From the place (Finnish: paikalta) we derive the name.
Author-email: Stefan Hagen <stefan@hagen.link>
Maintainer-email: Stefan Hagen <stefan@hagen.link>
License-Expression: MIT
Project-URL: Homepage, https://git.sr.ht/~sthagen/paikalta
Project-URL: Bug-Tracker, https://todo.sr.ht/~sthagen/paikalta
Project-URL: Documentation, https://codes.dilettant.life/docs/paikalta
Project-URL: Source-Code, https://git.sr.ht/~sthagen/paikalta
Project-URL: Test-Coverage, https://codes.dilettant.life/coverage/paikalta
Keywords: developer-tools,devops
Classifier: Development Status :: 4 - Beta
Classifier: Intended Audience :: Developers
Classifier: Programming Language :: Python :: 3.10
Classifier: Programming Language :: Python :: 3.11
Classifier: Programming Language :: Python :: 3.12
Classifier: Programming Language :: Python :: 3.13
Classifier: Programming Language :: Python :: 3.9
Requires-Python: >=3.9
License-File: LICENSE
Requires-Dist: msgspec>=0.18.4
Provides-Extra: dev
Requires-Dist: black; extra == "dev"
Requires-Dist: coverage; extra == "dev"
Requires-Dist: hypothesis; extra == "dev"
Requires-Dist: mypy; extra == "dev"
Requires-Dist: pytest; extra == "dev"
Requires-Dist: pytest-cov; extra == "dev"
Requires-Dist: pytest-flake8; extra == "dev"
Requires-Dist: ruff; extra == "dev"
Dynamic: license-file
